md_notes_cc/__init__.py
md_notes_cc/api_helper.py
md_notes_cc/configuration.py
md_notes_cc/decorators.py
md_notes_cc/md_notes_cc_client.py
md_notes_cc/controllers/__init__.py
md_notes_cc/controllers/base_controller.py
md_notes_cc/controllers/o_auth_authorization_controller.py
md_notes_cc/controllers/service_controller.py
md_notes_cc/controllers/user_controller.py
md_notes_cc/exceptions/__init__.py
md_notes_cc/exceptions/api_exception.py
md_notes_cc/exceptions/o_auth_provider_exception.py
md_notes_cc/http/__init__.py
md_notes_cc/http/http_call_back.py
md_notes_cc/http/http_client.py
md_notes_cc/http/http_context.py
md_notes_cc/http/http_method_enum.py
md_notes_cc/http/http_request.py
md_notes_cc/http/http_response.py
md_notes_cc/http/requests_client.py
md_notes_cc/http/auth/__init__.py
md_notes_cc/http/auth/o_auth_2.py
md_notes_cc/models/__init__.py
md_notes_cc/models/note.py
md_notes_cc/models/o_auth_provider_error_enum.py
md_notes_cc/models/o_auth_scope_enum.py
md_notes_cc/models/o_auth_token.py
md_notes_cc/models/service_status.py
md_notes_cc/models/user.py
MdNotes_CC-1.0.dist-info/LICENSE
MdNotes_CC-1.0.dist-info/METADATA
MdNotes_CC-1.0.dist-info/WHEEL
MdNotes_CC-1.0.dist-info/top_level.txt
MdNotes_CC-1.0.dist-info/RECORD
